timeflux_ui/__init__.py
timeflux_ui/nodes/__init__.py
timeflux_ui/nodes/ui.py
timeflux_ui/www/common/assets/css/bulma.css
timeflux_ui/www/common/assets/css/bulma.css.map
timeflux_ui/www/common/assets/css/bulma.min.css
timeflux_ui/www/common/assets/js/fa.js
timeflux_ui/www/common/assets/js/timeflux.js
timeflux_ui/www/common/assets/js/vue.js
timeflux_ui/www/monitor/index.html
timeflux_ui/www/monitor/assets/css/ui.css
timeflux_ui/www/monitor/assets/img/timeflux_logo_white.png
timeflux_ui/www/monitor/assets/js/smoothie.js
timeflux_ui/www/monitor/assets/js/ui.js
timeflux_ui-0.6.4.dist-info/LICENSE
timeflux_ui-0.6.4.dist-info/METADATA
timeflux_ui-0.6.4.dist-info/WHEEL
timeflux_ui-0.6.4.dist-info/top_level.txt
timeflux_ui-0.6.4.dist-info/RECORD
